processing_eeg_methods/__init__.py
processing_eeg_methods/classifiers_classes.py
processing_eeg_methods/data_classification.py
processing_eeg_methods/data_dataclass.py
processing_eeg_methods/data_loaders.py
processing_eeg_methods/data_utils.py
processing_eeg_methods/share.py
processing_eeg_methods/BigProject/GRU_probs.py
processing_eeg_methods/BigProject/LSTM_probs.py
processing_eeg_methods/NeuroTechX_dl_eeg/ShallowFBCSPNet_probs.py
processing_eeg_methods/NeuroTechX_dl_eeg/nn_Conv2d_probs.py
processing_eeg_methods/diffusion/diffE_evaluation.py
processing_eeg_methods/diffusion/diffE_models.py
processing_eeg_methods/diffusion/diffE_probs.py
processing_eeg_methods/diffusion/diffE_training.py
processing_eeg_methods/diffusion/diffE_utils.py
processing_eeg_methods/spatial_features/exercise_to_see_datasets_and_classifiers.py
processing_eeg_methods/spatial_features/simplified_spatial_features_probs.py
processing_eeg_methods/spatial_features/spatial_features_probs.py
processing_eeg_methods/time_features/EEGExtract.py
processing_eeg_methods/time_features/time_features_probs.py
EEG_Classifiers_Ensemble-0.1.6.dist-info/LICENSE
EEG_Classifiers_Ensemble-0.1.6.dist-info/METADATA
EEG_Classifiers_Ensemble-0.1.6.dist-info/WHEEL
EEG_Classifiers_Ensemble-0.1.6.dist-info/top_level.txt
EEG_Classifiers_Ensemble-0.1.6.dist-info/RECORD
