Metadata-Version: 2.1
Name: EEG-Classifiers-Ensemble
Version: 0.1.6
Summary: Tools for processing and classifying EEG tasks in real-time.
Home-page: https://github.com/AlmaCuevas/Ensemble-EEG
Author: Alma Cuevas
Author-email: Alma Cuevas <almarosa.arcr@gmail.com>
License: MIT License
Keywords: EEG,classification,ERP,feature extraction,transforms
Requires-Python: <4,>=3.10
License-File: LICENSE
